visorRobot/__init__.py
visorRobot/visor.py
visorRobot11-0.0.1.dist-info/METADATA
visorRobot11-0.0.1.dist-info/WHEEL
visorRobot11-0.0.1.dist-info/top_level.txt
visorRobot11-0.0.1.dist-info/RECORD
